curves/__init__.py
curves/__version__.py
curves/_common.py
curves/adjustments.py
curves/bootstrap.py
curves/contract_period.py
curves/hyperbolic_tension_spline.py
curves/max_smoothness_spline.py
curves/weighting.py
curves/lib/Cmdty.Curves.dll
curves/lib/Cmdty.Curves.pdb
curves/lib/Cmdty.TimePeriodValueTypes.dll
curves/lib/Cmdty.TimeSeries.dll
curves/lib/JetBrains.Annotations.dll
curves/lib/MathNet.Numerics.dll
curves/lib/System.Runtime.CompilerServices.Unsafe.dll
curves-2.0.0.dist-info/LICENSE.md
curves-2.0.0.dist-info/METADATA
curves-2.0.0.dist-info/WHEEL
curves-2.0.0.dist-info/top_level.txt
curves-2.0.0.dist-info/RECORD
