Metadata-Version: 2.1
Name: curves
Version: 2.0.0
Summary: Tools for building commodity forward, swaps, and futures curves.
Home-page: https://github.com/cmdty/curves
Author: Jake Fowler
Author-email: jake@cmdty.co.uk
License: UNKNOWN
Keywords: commodities trading curves oil gas power quantitative finance
Platform: UNKNOWN
Classifier: Development Status :: 5 - Production/Stable
Classifier: Programming Language :: C#
Classifier: Intended Audience :: Developers
Classifier: Intended Audience :: Financial and Insurance Industry
Classifier: Programming Language :: Python :: 3
Classifier: Programming Language :: Python :: 3.7
Classifier: Programming Language :: Python :: 3.8
Classifier: Programming Language :: Python :: 3.9
Classifier: Programming Language :: Python :: 3.10
Classifier: Programming Language :: Python :: 3.11
Classifier: Programming Language :: Python :: 3.12
Classifier: License :: OSI Approved :: MIT License
Classifier: Operating System :: Microsoft :: Windows
Classifier: Operating System :: POSIX :: Linux
Classifier: Operating System :: MacOS :: MacOS X
Classifier: Topic :: Office/Business :: Financial
Classifier: Topic :: Office/Business :: Financial :: Investment
Classifier: Topic :: Scientific/Engineering :: Mathematics
Classifier: Topic :: Software Development :: Libraries :: Python Modules
Requires-Python: >=3.7, <3.13
Requires-Dist: pythonnet <3.1.0a0,>=3.0.1
Requires-Dist: pandas <2.3.0a0,>=1.0.0
